cross_locs/__init__.py
cross_locs/data/elrs.pkl
cross_locs/explore/__init__.py
cross_locs/explore/explore.py
cross_locs/locs/__init__.py
cross_locs/locs/constants.py
cross_locs/locs/exceptions.py
cross_locs/locs/loader.py
cross_locs/locs/locs.py
cross_locs/locs/mileage.py
cross_locs/locs/processor.py
cross_locs/locs/validator.py
cross_locs/models/__init__.py
cross_locs/models/elr.py
cross_locs-0.1.10.dist-info/METADATA
cross_locs-0.1.10.dist-info/WHEEL
cross_locs-0.1.10.dist-info/RECORD
