Metadata-Version: 2.3
Name: cross-locs
Version: 0.1.10
Summary: Python library focused on location-oriented operations
License: MIT
Author: Fedor Sulitskiy
Author-email: fedor@crosstech.co.uk
Requires-Python: >=3.11,<4.0
Classifier: License :: OSI Approved :: MIT License
Classifier: Programming Language :: Python :: 3
Classifier: Programming Language :: Python :: 3.11
Classifier: Programming Language :: Python :: 3.12
Classifier: Programming Language :: Python :: 3.13
Requires-Dist: folium (>=0.19.5,<0.20.0)
Requires-Dist: geopandas (>=1.0.1,<2.0.0)
Requires-Dist: google-cloud-storage (>=3.1.0,<4.0.0)
Requires-Dist: mapclassify (>=2.8.1,<3.0.0)
Requires-Dist: matplotlib (>=3.10.1,<4.0.0)
Requires-Dist: pandera (>=0.23.0,<0.24.0)
